[
  {
    "start": 0.0,
    "text": "How can I improve my English speaking?"
  },
  {
    "start": 4.2,
    "text": "The answer is to speak!"
  },
  {
    "start": 6.6,
    "text": "Luckily, you don't have to go to the US or the UK to practice your English speaking."
  },
  {
    "start": 13.9,
    "text": "Now I am in Ite1 and there are many foreigners here."
  },
  {
    "start": 17.9,
    "text": "So you can come here and practice your English speaking."
  },
  {
    "start": 22.2,
    "text": "Today I am with my husband who is Korean and he's going to complete some missions here in"
  },
  {
    "start": 29.9,
    "text": "Ite1 to see if he can practice his English without ever leaving the country."
  },
  {
    "start": 36.2,
    "text": "First mission is to order coffee and you must ask three questions while ordering."
  },
  {
    "start": 43.3,
    "text": "How do you feel about doing these missions today?"
  },
  {
    "start": 46.8,
    "text": "I usually go on coffee while ordering, so I'm a little shy."
  },
  {
    "start": 50.4,
    "text": "Maybe by the end of the day, you'll get more confident."
  },
  {
    "start": 53.0,
    "text": "Let's go get some coffee."
  },
  {
    "start": 54.2,
    "text": "We just got a table at Plant Cafe."
  },
  {
    "start": 61.8,
    "text": "I'm going to stay at the table while Hong goes up to order by himself and asks his three questions."
  },
  {
    "start": 71.7,
    "text": "Can I order?"
  },
  {
    "start": 72.6,
    "text": "Yes, yes."
  },
  {
    "start": 73.8,
    "text": "I would like to have a pumpkin spice latte."
  },
  {
    "start": 76.1,
    "text": "Pumpkin spice latte?"
  },
  {
    "start": 77.0,
    "text": "Yes."
  },
  {
    "start": 77.9,
    "text": "Oh, no, sorry."
  },
  {
    "start": 79.0,
    "text": "Half please."
  },
  {
    "start": 79.8,
    "text": "Half please."
  },
  {
    "start": 80.2,
    "text": "Is it your cooking review?"
  },
  {
    "start": 82.2,
    "text": "Do you have almond milk?"
  },
  {
    "start": 84.2,
    "text": "Oh, almond milk."
  },
  {
    "start": 84.9,
    "text": "Yes."
  },
  {
    "start": 85.4,
    "text": "You want to add whipping cream on top?"
  },
  {
    "start": 87.0,
    "text": "No, thanks."
  },
  {
    "start": 88.2,
    "text": "Kelly, do you want whipped cream on top or no?"
  },
  {
    "start": 90.6,
    "text": "Okay, sorry."
  },
  {
    "start": 91.5,
    "text": "Yeah."
  },
  {
    "start": 92.3,
    "text": "Whipped cream, please."
  },
  {
    "start": 93.2,
    "text": "And I would like to have a teaser."
  },
  {
    "start": 94.8,
    "text": "Do you guys have any good teaser?"
  },
  {
    "start": 97.0,
    "text": "Recommend with the pumpkin spice?"
  },
  {
    "start": 99.5,
    "text": "Yeah, but everything you see here, we make it."
  },
  {
    "start": 103.4,
    "text": "Oh, homemade?"
  },
  {
    "start": 104.2,
    "text": "Yeah, homemade."
  },
  {
    "start": 104.9,
    "text": "It's really difficult because everything is so delicious."
  },
  {
    "start": 108.4,
    "text": "You sound like I need to order more than one."
  },
  {
    "start": 111.0,
    "text": "Okay, maybe I'll choose one and can you choose one for me then?"
  },
  {
    "start": 114.9,
    "text": "Yeah, I'll choose the blueberry almond crumble."
  },
  {
    "start": 118.4,
    "text": "It's really good."
  },
  {
    "start": 119.4,
    "text": "I think so."
  },
  {
    "start": 120.4,
    "text": "I like chocolate, you like something fruity."
  },
  {
    "start": 123.6,
    "text": "I like fruity one."
  },
  {
    "start": 124.7,
    "text": "The lemon or grape is really good."
  },
  {
    "start": 127.0,
    "text": "Out to the lemon."
  },
  {
    "start": 128.6,
    "text": "Lemon?"
  },
  {
    "start": 128.8,
    "text": "Yeah, yeah."
  },
  {
    "start": 129.5,
    "text": "Can I have one iced coffee too?"
  },
  {
    "start": 132.1,
    "text": "Just iced Americano."
  },
  {
    "start": 132.7,
    "text": "Yes."
  },
  {
    "start": 133.4,
    "text": "Do you have different beans too or just one bean?"
  },
  {
    "start": 136.8,
    "text": "This one."
  },
  {
    "start": 137.2,
    "text": "Okay, okay."
  },
  {
    "start": 138.2,
    "text": "Thank you."
  },
  {
    "start": 139.2,
    "text": "Thank you so much."
  },
  {
    "start": 140.4,
    "text": "You're so good."
  },
  {
    "start": 141.4,
    "text": "You're so good."
  },
  {
    "start": 142.3,
    "text": "Nailed it."
  },
  {
    "start": 143.0,
    "text": "Nailed it."
  },
  {
    "start": 143.8,
    "text": "You nailed that recommendation."
  },
  {
    "start": 145.4,
    "text": "Mission one, the weird pastifying colors."
  },
  {
    "start": 149.9,
    "text": "Good job."
  },
  {
    "start": 150.5,
    "text": "I was actually really impressed."
  },
  {
    "start": 151.9,
    "text": "So I was sitting there and could hear him asking all these questions."
  },
  {
    "start": 155.8,
    "text": "I tried."
  },
  {
    "start": 156.6,
    "text": "So now we're on to our second location for Mission 2."
  },
  {
    "start": 161.3,
    "text": "We are going to Cali Kitchen, which is a popular American bar and restaurant here."
  },
  {
    "start": 168.2,
    "text": "And the next mission is to try doing a bit of small talk"
  },
  {
    "start": 174.5,
    "text": "with the owner or some of the staff."
  },
  {
    "start": 177.6,
    "text": "I usually like delivery."
  },
  {
    "start": 179.3,
    "text": "They're there."
  },
  {
    "start": 180.7,
    "text": "No interaction."
  },
  {
    "start": 181.9,
    "text": "I don't like interaction."
  },
  {
    "start": 183.4,
    "text": "I'm letting the bird out of the next here."
  },
  {
    "start": 186.1,
    "text": "Going in by yourself."
  },
  {
    "start": 187.5,
    "text": "And in English?"
  },
  {
    "start": 188.5,
    "text": "No, no, no, no."
  },
  {
    "start": 190.2,
    "text": "Challenge."
  },
  {
    "start": 191.4,
    "text": "That's it."
  },
  {
    "start": 193.0,
    "text": "Go."
  },
  {
    "start": 193.6,
    "text": "Bye."
  },
  {
    "start": 194.5,
    "text": "Bye."
  },
  {
    "start": 196.3,
    "text": "Oh."
  },
  {
    "start": 198.5,
    "text": "What's the most popular menu here?"
  },
  {
    "start": 200.5,
    "text": "Most popular."
  },
  {
    "start": 201.6,
    "text": "Yeah."
  },
  {
    "start": 202.7,
    "text": "This one is like one curry and then it's like the butter."
  },
  {
    "start": 206.8,
    "text": "What about taco?"
  },
  {
    "start": 207.8,
    "text": "Tiger."
  },
  {
    "start": 208.5,
    "text": "You have a chicken in the money."
  },
  {
    "start": 209.9,
    "text": "Okay."
  },
  {
    "start": 210.7,
    "text": "I will recommend anything with carnitas because most carnitas are good."
  },
  {
    "start": 214.6,
    "text": "Good."
  },
  {
    "start": 214.9,
    "text": "Okay."
  },
  {
    "start": 215.4,
    "text": "Maybe just a burger and two pieces of carnitas."
  },
  {
    "start": 219.5,
    "text": "And do you guys have any tips or tips?"
  },
  {
    "start": 222.2,
    "text": "I don't have a lot of tips in this menu."
  },
  {
    "start": 224.2,
    "text": "I would have a lot of tips with macaramoli."
  },
  {
    "start": 227.4,
    "text": "Welcome."
  },
  {
    "start": 227.8,
    "text": "Yeah."
  },
  {
    "start": 228.3,
    "text": "And cocktail please."
  },
  {
    "start": 229.5,
    "text": "Thank you."
  },
  {
    "start": 230.4,
    "text": "I was wondering the guy from the TV."
  },
  {
    "start": 233.5,
    "text": "Was having a burger?"
  },
  {
    "start": 234.9,
    "text": "Yeah."
  },
  {
    "start": 235.8,
    "text": "Which burger was out of this section?"
  },
  {
    "start": 237.4,
    "text": "It was a butter one that I ordered."
  },
  {
    "start": 242.2,
    "text": "So I need to be in here."
  },
  {
    "start": 244.6,
    "text": "Be graduate from here?"
  },
  {
    "start": 245.9,
    "text": "Yeah."
  },
  {
    "start": 246.7,
    "text": "Wow."
  },
  {
    "start": 247.6,
    "text": "Brought to you here."
  },
  {
    "start": 249.4,
    "text": "Korea."
  },
  {
    "start": 252.4,
    "text": "Korea."
  },
  {
    "start": 253.4,
    "text": "The patty is evenly cooked."
  },
  {
    "start": 256.0,
    "text": "Very sophisticated, you know."
  },
  {
    "start": 257.7,
    "text": "Cook to perfection."
  },
  {
    "start": 259.4,
    "text": "What's the head?"
  },
  {
    "start": 260.4,
    "text": "This is so good."
  },
  {
    "start": 262.2,
    "text": "Wow."
  },
  {
    "start": 262.6,
    "text": "It's like salty but in a way that like pickles my brain."
  },
  {
    "start": 267.2,
    "text": "It's so good."
  },
  {
    "start": 268.2,
    "text": "I never thought of butter as a topping for a burger."
  },
  {
    "start": 271.8,
    "text": "That someone's pick source right."
  },
  {
    "start": 274.0,
    "text": "He was really right."
  },
  {
    "start": 276.4,
    "text": "Yeah, it was really good."
  },
  {
    "start": 277.8,
    "text": "Would you mind if we get a box or they take out or something?"
  },
  {
    "start": 281.2,
    "text": "I think you'd like to see it."
  },
  {
    "start": 282.8,
    "text": "Bye."
  },
  {
    "start": 284.0,
    "text": "So lovely."
  },
  {
    "start": 285.4,
    "text": "I wanted to be her friend."
  },
  {
    "start": 287.0,
    "text": "Well, I am her friend, so."
  },
  {
    "start": 290.6,
    "text": "Wow."
  },
  {
    "start": 291.2,
    "text": "I can't say for sure because I wasn't there the whole time."
  },
  {
    "start": 296.0,
    "text": "But I think it was a success."
  },
  {
    "start": 297.8,
    "text": "Was it awkward like starting the small talk?"
  },
  {
    "start": 300.4,
    "text": "I think at first a little bit but she was very friendly."
  },
  {
    "start": 304.0,
    "text": "For the small talk, it was the opening time."
  },
  {
    "start": 306.2,
    "text": "Always can you recommend?"
  },
  {
    "start": 308.2,
    "text": "That's good though."
  },
  {
    "start": 309.0,
    "text": "Because small talk changes so much depending on the content."
  },
  {
    "start": 312.8,
    "text": "I think it's good."
  },
  {
    "start": 313.4,
    "text": "You're starting conversation based on the situation."
  },
  {
    "start": 317.0,
    "text": "Good job."
  },
  {
    "start": 317.5,
    "text": "Good success."
  },
  {
    "start": 318.8,
    "text": "Now we are heading to a bar."
  },
  {
    "start": 321.4,
    "text": "And this is the hardest challenge."
  },
  {
    "start": 323.8,
    "text": "Your mission is to make a new friend."
  },
  {
    "start": 327.4,
    "text": "So not the staff, not a worker there,"
  },
  {
    "start": 330.6,
    "text": "but just another customer."
  },
  {
    "start": 333.2,
    "text": "You have to just approach some other customers and make a friend."
  },
  {
    "start": 337.2,
    "text": "I haven't done this for like, I don't know, 10 years."
  },
  {
    "start": 341.0,
    "text": "Drink a beer and get your liquid courage."
  },
  {
    "start": 343.4,
    "text": "Maybe I need an alcohol."
  },
  {
    "start": 345.3,
    "text": "I'm scared to see what condition you're going to be in."
  },
  {
    "start": 348.2,
    "text": "I'm going to pick you up."
  },
  {
    "start": 349.1,
    "text": "Good."
  },
  {
    "start": 349.9,
    "text": "All right."
  },
  {
    "start": 350.6,
    "text": "Let's see how it goes."
  },
  {
    "start": 351.8,
    "text": "You're leaving me in the dust."
  },
  {
    "start": 353.0,
    "text": "Go, go, go, go, go, go, go, go."
  },
  {
    "start": 355.6,
    "text": "I'm too sober for this."
  },
  {
    "start": 358.2,
    "text": "There's no one."
  },
  {
    "start": 359.5,
    "text": "Hey."
  },
  {
    "start": 360.4,
    "text": "How many do you want?"
  },
  {
    "start": 361.4,
    "text": "Just me."
  },
  {
    "start": 362.2,
    "text": "I'm guessing whatever you want."
  },
  {
    "start": 363.5,
    "text": "Can I see that bar too?"
  },
  {
    "start": 364.6,
    "text": "Of course."
  },
  {
    "start": 365.0,
    "text": "Yes."
  },
  {
    "start": 365.7,
    "text": "Thank you."
  },
  {
    "start": 366.6,
    "text": "So today, we have nachos on special."
  },
  {
    "start": 369.6,
    "text": "And also we have two tacos for eight."
  },
  {
    "start": 372.1,
    "text": "Do you have a drink menu too?"
  },
  {
    "start": 373.7,
    "text": "Drink menu?"
  },
  {
    "start": 374.5,
    "text": "Yes."
  },
  {
    "start": 374.9,
    "text": "So don't try it with a new beer."
  },
  {
    "start": 377.0,
    "text": "I'll have that."
  },
  {
    "start": 377.9,
    "text": "Thank you."
  },
  {
    "start": 378.9,
    "text": "Do you want to try any shots?"
  },
  {
    "start": 380.2,
    "text": "I was experimenting for a halloween."
  },
  {
    "start": 382.2,
    "text": "Oh, wow."
  },
  {
    "start": 383.0,
    "text": "Yeah, sure."
  },
  {
    "start": 383.8,
    "text": "Uh, what's this crazy looking thing in this one?"
  },
  {
    "start": 387.2,
    "text": "This one is Tabasco with vodka."
  },
  {
    "start": 389.4,
    "text": "You should drink it without thinking."
  },
  {
    "start": 390.8,
    "text": "Okay."
  },
  {
    "start": 391.3,
    "text": "Did you try it?"
  },
  {
    "start": 391.9,
    "text": "Yeah, I tried it different."
  },
  {
    "start": 393.0,
    "text": "Yeah?"
  },
  {
    "start": 393.2,
    "text": "Oh, thank you."
  },
  {
    "start": 394.0,
    "text": "What did you try?"
  },
  {
    "start": 395.0,
    "text": "I status."
  },
  {
    "start": 397.0,
    "text": "Cheers."
  },
  {
    "start": 397.8,
    "text": "Cheers."
  },
  {
    "start": 400.3,
    "text": "Wow."
  },
  {
    "start": 400.8,
    "text": "That was spicy."
  },
  {
    "start": 401.5,
    "text": "Yeah."
  },
  {
    "start": 402.2,
    "text": "Oh."
  },
  {
    "start": 403.1,
    "text": "What would you recommend out of this?"
  },
  {
    "start": 404.9,
    "text": "Out of the beef."
  },
  {
    "start": 405.7,
    "text": "Beef one?"
  },
  {
    "start": 406.2,
    "text": "Yeah."
  },
  {
    "start": 406.5,
    "text": "Okay."
  },
  {
    "start": 406.6,
    "text": "I'll check your recommendation."
  },
  {
    "start": 408.1,
    "text": "Can I have a beef pie?"
  },
  {
    "start": 409.7,
    "text": "You come here pretty often?"
  },
  {
    "start": 411.2,
    "text": "Yeah, yeah."
  },
  {
    "start": 412.1,
    "text": "Across the street."
  },
  {
    "start": 413.0,
    "text": "Oh, okay."
  },
  {
    "start": 413.8,
    "text": "You're kind of off today, early?"
  },
  {
    "start": 415.5,
    "text": "Yeah, I get off when you were 30."
  },
  {
    "start": 417.2,
    "text": "Oh, nice."
  },
  {
    "start": 417.9,
    "text": "Happy hour, too?"
  },
  {
    "start": 419.1,
    "text": "That's a good combo."
  },
  {
    "start": 420.3,
    "text": "Not bad at all."
  },
  {
    "start": 422.1,
    "text": "So, you moved very recently?"
  },
  {
    "start": 426.1,
    "text": "Yeah, so it started to take your seat out."
  },
  {
    "start": 428.6,
    "text": "Oh, home, by the way."
  },
  {
    "start": 430.1,
    "text": "Nice to meet you."
  },
  {
    "start": 431.0,
    "text": "Ryan."
  },
  {
    "start": 431.8,
    "text": "Ryan."
  },
  {
    "start": 432.2,
    "text": "I see you."
  },
  {
    "start": 434.2,
    "text": "How's the living around here?"
  },
  {
    "start": 435.8,
    "text": "I always wanted to live around this area"
  },
  {
    "start": 437.9,
    "text": "if I'd never had a chance."
  },
  {
    "start": 439.1,
    "text": "This was like Canada."
  },
  {
    "start": 440.3,
    "text": "Oh, you're from Canada?"
  },
  {
    "start": 442.1,
    "text": "I'm from Toronto."
  },
  {
    "start": 443.2,
    "text": "Toronto."
  },
  {
    "start": 444.4,
    "text": "My wife's from Michigan?"
  },
  {
    "start": 445.8,
    "text": "Michigan."
  },
  {
    "start": 446.5,
    "text": "Not too far from Canada."
  },
  {
    "start": 448.2,
    "text": "Also, we have pineapple margaritas today."
  },
  {
    "start": 451.4,
    "text": "Sure."
  },
  {
    "start": 451.9,
    "text": "Would you drink margarita, too?"
  },
  {
    "start": 453.5,
    "text": "A bipro."
  },
  {
    "start": 454.3,
    "text": "Us."
  },
  {
    "start": 455.0,
    "text": "I love water in this environment."
  },
  {
    "start": 456.6,
    "text": "Yeah."
  },
  {
    "start": 457.7,
    "text": "You have to see."
  },
  {
    "start": 458.5,
    "text": "Do you have any like favorite guys?"
  },
  {
    "start": 459.9,
    "text": "You're an era?"
  },
  {
    "start": 460.7,
    "text": "Okay."
  },
  {
    "start": 461.1,
    "text": "This is like a champion."
  },
  {
    "start": 462.7,
    "text": "He's like came in from kickboxing."
  },
  {
    "start": 464.7,
    "text": "He has like the hardest punch in history."
  },
  {
    "start": 468.6,
    "text": "Yeah."
  },
  {
    "start": 469.0,
    "text": "Do you know the cram zombie?"
  },
  {
    "start": 470.5,
    "text": "Oh, yeah."
  },
  {
    "start": 471.1,
    "text": "Yeah, yeah, yeah."
  },
  {
    "start": 472.0,
    "text": "That bike was his last one."
  },
  {
    "start": 474.0,
    "text": "Yeah, the last one."
  },
  {
    "start": 474.8,
    "text": "When the whole audience came to the cram,"
  },
  {
    "start": 477.0,
    "text": "yeah, yeah."
  },
  {
    "start": 480.4,
    "text": "Yeah, that was crazy."
  },
  {
    "start": 486.5,
    "text": "This show's crazy."
  },
  {
    "start": 487.4,
    "text": "I like it."
  },
  {
    "start": 488.2,
    "text": "Have you watched?"
  },
  {
    "start": 489.0,
    "text": "I'm obsessed with it."
  },
  {
    "start": 489.8,
    "text": "Yeah."
  },
  {
    "start": 490.2,
    "text": "I think it made it really well."
  },
  {
    "start": 491.4,
    "text": "Yeah."
  },
  {
    "start": 492.1,
    "text": "I've heard all the chefs here,"
  },
  {
    "start": 494.2,
    "text": "like book food until the end of the year,"
  },
  {
    "start": 496.6,
    "text": "especially the semi-final,"
  },
  {
    "start": 498.7,
    "text": "the tofu one."
  },
  {
    "start": 499.8,
    "text": "That's crazy."
  },
  {
    "start": 501.0,
    "text": "Yeah."
  },
  {
    "start": 501.8,
    "text": "You're never going to see that in America."
  },
  {
    "start": 503.5,
    "text": "Exactly."
  },
  {
    "start": 504.2,
    "text": "Park food coming from the ceiling."
  },
  {
    "start": 505.9,
    "text": "Thank you."
  },
  {
    "start": 506.6,
    "text": "You're one of a part."
  },
  {
    "start": 507.5,
    "text": "Ah."
  },
  {
    "start": 509.7,
    "text": "Wow, it's good."
  },
  {
    "start": 510.7,
    "text": "It's good, eh?"
  },
  {
    "start": 511.4,
    "text": "It's really good."
  },
  {
    "start": 512.2,
    "text": "My grandmother's this big."
  },
  {
    "start": 513.5,
    "text": "Do you cook sometimes at home?"
  },
  {
    "start": 514.9,
    "text": "Yeah, I enjoy."
  },
  {
    "start": 515.8,
    "text": "You do?"
  },
  {
    "start": 516.4,
    "text": "Yeah."
  },
  {
    "start": 517.0,
    "text": "You have like your special own."
  },
  {
    "start": 519.2,
    "text": "Korean food is Galbi gym."
  },
  {
    "start": 521.0,
    "text": "Yeah, there's..."
  },
  {
    "start": 522.5,
    "text": "I've got a good restaurant."
  },
  {
    "start": 523.4,
    "text": "No kidding."
  },
  {
    "start": 524.3,
    "text": "Really?"
  },
  {
    "start": 525.2,
    "text": "It's a lot of work."
  },
  {
    "start": 526.2,
    "text": "I made it for my eggs."
  },
  {
    "start": 528.0,
    "text": "Yeah?"
  },
  {
    "start": 528.8,
    "text": "Like, when I made it, I brought it over."
  },
  {
    "start": 530.7,
    "text": "This time mom would send me Galbi gym."
  },
  {
    "start": 532.6,
    "text": "Oh, yes."
  },
  {
    "start": 533.4,
    "text": "Send Galbi gym to there."
  },
  {
    "start": 534.6,
    "text": "Oh."
  },
  {
    "start": 535.4,
    "text": "And then brother, this story like,"
  },
  {
    "start": 537.2,
    "text": "you like yours more."
  },
  {
    "start": 539.2,
    "text": "We can't do their mom."
  },
  {
    "start": 540.7,
    "text": "Whoa."
  },
  {
    "start": 541.4,
    "text": "I made this."
  },
  {
    "start": 542.1,
    "text": "You made this?"
  },
  {
    "start": 542.9,
    "text": "Slow roast, gochujang, take it."
  },
  {
    "start": 545.0,
    "text": "It looks like from the restaurant."
  },
  {
    "start": 547.7,
    "text": "Ryan made this."
  },
  {
    "start": 549.1,
    "text": "Experiment."
  },
  {
    "start": 550.0,
    "text": "Okay, okay."
  },
  {
    "start": 550.7,
    "text": "It's experiment."
  },
  {
    "start": 551.5,
    "text": "She said, don't think."
  },
  {
    "start": 553.3,
    "text": "Just keep it during two, three, two, three."
  },
  {
    "start": 556.8,
    "text": "Thank you."
  },
  {
    "start": 557.4,
    "text": "Thank you so much."
  },
  {
    "start": 558.6,
    "text": "Ooh, that is nice."
  },
  {
    "start": 560.3,
    "text": "How was it?"
  },
  {
    "start": 561.3,
    "text": "Really good."
  },
  {
    "start": 562.8,
    "text": "Are you from Kazakhstan?"
  },
  {
    "start": 564.2,
    "text": "Yeah."
  },
  {
    "start": 564.9,
    "text": "How long have you been in Korea?"
  },
  {
    "start": 566.2,
    "text": "Three years now."
  },
  {
    "start": 567.2,
    "text": "That's cool."
  },
  {
    "start": 568.2,
    "text": "Have you been working at Sausage Parkwayo?"
  },
  {
    "start": 570.4,
    "text": "Almost."
  },
  {
    "start": 571.4,
    "text": "Seven, eight months."
  },
  {
    "start": 572.4,
    "text": "Okay."
  },
  {
    "start": 573.0,
    "text": "But I used to be a regular here."
  },
  {
    "start": 575.0,
    "text": "Okay."
  },
  {
    "start": 575.4,
    "text": "We got a million, one bet."
  },
  {
    "start": 577.1,
    "text": "Really?"
  },
  {
    "start": 577.9,
    "text": "$100 million."
  },
  {
    "start": 579.7,
    "text": "Is it?"
  },
  {
    "start": 580.6,
    "text": "Is it one or a dollar?"
  },
  {
    "start": 582.2,
    "text": "You heard it, bro."
  },
  {
    "start": 584.2,
    "text": "We got it right here."
  },
  {
    "start": 585.4,
    "text": "I'm gonna call it that."
  },
  {
    "start": 586.5,
    "text": "We got it right here."
  },
  {
    "start": 587.4,
    "text": "Ryan."
  },
  {
    "start": 588.0,
    "text": "Cheers."
  },
  {
    "start": 588.6,
    "text": "Cheers."
  },
  {
    "start": 589.2,
    "text": "Cheers."
  },
  {
    "start": 591.2,
    "text": "Cheers."
  },
  {
    "start": 593.0,
    "text": "Ryan, do you do inside or any type of social media?"
  },
  {
    "start": 597.3,
    "text": "Maybe we can grab."
  },
  {
    "start": 598.3,
    "text": "Yeah."
  },
  {
    "start": 599.0,
    "text": "For sure, for sure."
  },
  {
    "start": 599.9,
    "text": "I should do you have any like,"
  },
  {
    "start": 601.3,
    "text": "Instagram or something then?"
  },
  {
    "start": 602.6,
    "text": "Yeah."
  },
  {
    "start": 603.4,
    "text": "But my stories are dumb, so I don't mind."
  },
  {
    "start": 606.8,
    "text": "Do you want a bad food stomach?"
  },
  {
    "start": 608.4,
    "text": "Yeah."
  },
  {
    "start": 609.8,
    "text": "Come on."
  },
  {
    "start": 612.2,
    "text": "Thank you, Ryan."
  },
  {
    "start": 613.0,
    "text": "Thank you."
  },
  {
    "start": 613.5,
    "text": "Appreciate it."
  },
  {
    "start": 614.3,
    "text": "Thank you for the shot."
  },
  {
    "start": 615.5,
    "text": "I shot."
  },
  {
    "start": 616.1,
    "text": "Really funny."
  },
  {
    "start": 617.2,
    "text": "I love the whole pool you gave me."
  },
  {
    "start": 618.9,
    "text": "Thank you."
  },
  {
    "start": 619.4,
    "text": "Appreciate it."
  },
  {
    "start": 620.0,
    "text": "Your face is looking a little red."
  },
  {
    "start": 622.2,
    "text": "All right."
  },
  {
    "start": 628.2,
    "text": "That's it for today."
  },
  {
    "start": 630.4,
    "text": "Practicing English in Itaewan."
  },
  {
    "start": 633.6,
    "text": "So what did you learn from today?"
  },
  {
    "start": 635.4,
    "text": "I was really shy at first,"
  },
  {
    "start": 637.2,
    "text": "but we are pretty friendly and open up to me."
  },
  {
    "start": 640.5,
    "text": "Eventually, at the bar, I made good friends,"
  },
  {
    "start": 643.2,
    "text": "so I might go back to bar."
  },
  {
    "start": 645.2,
    "text": "Do you recommend Koreans who are wanting"
  },
  {
    "start": 647.8,
    "text": "to practice their English?"
  },
  {
    "start": 649.4,
    "text": "Come to Itaewan?"
  },
  {
    "start": 650.4,
    "text": "For sure."
  },
  {
    "start": 651.0,
    "text": "A lot of people here are open to make a new friend."
  },
  {
    "start": 654.1,
    "text": "I think too."
  },
  {
    "start": 655.2,
    "text": "If you want to practice speaking,"
  },
  {
    "start": 657.4,
    "text": "but you're a little bit scared and shy,"
  },
  {
    "start": 659.8,
    "text": "do it kind of how you did it today with levels."
  },
  {
    "start": 662.9,
    "text": "Take baby steps."
  },
  {
    "start": 664.1,
    "text": "Just try ordering coffee and asking a few questions."
  },
  {
    "start": 667.8,
    "text": "Maybe a tip will be trying to find their interest."
  },
  {
    "start": 671.4,
    "text": "So for example, Ryan was interested in UFC"
  },
  {
    "start": 675.0,
    "text": "and then a cooking show."
  },
  {
    "start": 676.4,
    "text": "So we were kind of talking about the topic"
  },
  {
    "start": 679.3,
    "text": "and he talked more and more and more."
  },
  {
    "start": 682.0,
    "text": "That's a good tip."
  },
  {
    "start": 682.9,
    "text": "Well, was today fun?"
  },
  {
    "start": 684.5,
    "text": "It was fun."
  },
  {
    "start": 685.5,
    "text": "Yeah, I don't think I have to ask that question."
  },
  {
    "start": 687.0,
    "text": "I think it's obvious."
  },
  {
    "start": 688.3,
    "text": "It's so good today."
  },
  {
    "start": 689.4,
    "text": "I'm so proud of you."
  },
  {
    "start": 690.6,
    "text": "Thank you."
  },
  {
    "start": 691.0,
    "text": "I feel more confident right now."
  },
  {
    "start": 692.5,
    "text": "I feel like I can do more."
  },
  {
    "start": 693.8,
    "text": "I can tell you're talking a lot more."
  },
  {
    "start": 695.5,
    "text": "I hope you enjoyed our video today."
  },
  {
    "start": 697.4,
    "text": "We're going to have a lot more videos like this."
  },
  {
    "start": 700.1,
    "text": "Come in your way."
  },
  {
    "start": 701.1,
    "text": "Make sure to like this video."
  },
  {
    "start": 702.9,
    "text": "Comment below."
  },
  {
    "start": 703.9,
    "text": "Subscribe to our channel."
  },
  {
    "start": 705.6,
    "text": "And check out the pinned comment."
  },
  {
    "start": 708.5,
    "text": "Thank you everyone."
  },
  {
    "start": 709.3,
    "text": "And we will see you next time."
  },
  {
    "start": 710.9,
    "text": "Bye."
  },
  {
    "start": 711.8,
    "text": "Thank you."
  }
]