[
  {
    "start": 0.08,
    "text": "It was like a situationship. That was a"
  },
  {
    "start": 2.48,
    "text": "huge turnoff."
  },
  {
    "start": 3.84,
    "text": ">> My type."
  },
  {
    "start": 4.88,
    "text": ">> Your type"
  },
  {
    "start": 6.0,
    "text": ">> would be."
  },
  {
    "start": 8.88,
    "text": "Oh,"
  },
  {
    "start": 10.48,
    "text": ">> hello."
  },
  {
    "start": 11.2,
    "text": ">> Hey, are you free tonight?"
  },
  {
    "start": 12.88,
    "text": ">> Maybe. What's up?"
  },
  {
    "start": 14.24,
    "text": ">> I was thinking we could go out dinner"
  },
  {
    "start": 16.4,
    "text": "and maybe a movie."
  },
  {
    "start": 17.6,
    "text": ">> A, that sounds fun. Let me check."
  },
  {
    "start": 21.199,
    "text": ">> Yeah, I think I can squeeze you in."
  },
  {
    "start": 23.439,
    "text": ">> Perfect. [clears throat] See you"
  },
  {
    "start": 24.32,
    "text": "tonight."
  },
  {
    "start": 24.88,
    "text": ">> Sounds good. Bye."
  },
  {
    "start": 28.0,
    "text": "Get ready with me to go on a date with"
  },
  {
    "start": 30.48,
    "text": "my husband. My husband and I have been"
  },
  {
    "start": 33.84,
    "text": "together for 12 years and married for"
  },
  {
    "start": 36.719,
    "text": "three. We live together, work together,"
  },
  {
    "start": 40.239,
    "text": "and basically do everything together,"
  },
  {
    "start": 42.879,
    "text": "but it's rare for us to go on an actual"
  },
  {
    "start": 45.84,
    "text": "date. So, I'm really excited. We're"
  },
  {
    "start": 48.239,
    "text": "going out for drinks, dinner, and a"
  },
  {
    "start": 51.36,
    "text": "movie. So, it's a very classic date"
  },
  {
    "start": 53.92,
    "text": "tonight."
  },
  {
    "start": 56.0,
    "text": "Back in high school, I had the biggest"
  },
  {
    "start": 58.64,
    "text": "crush on the same guy for years and he"
  },
  {
    "start": 62.719,
    "text": "finally asked me out and I was so"
  },
  {
    "start": 65.439,
    "text": "excited. We had a lot of mutual friends,"
  },
  {
    "start": 68.88,
    "text": "so we hung out at parties, but we never"
  },
  {
    "start": 71.6,
    "text": "hung out one-on-one before, so I was"
  },
  {
    "start": 74.32,
    "text": "really nervous and this was kind of a"
  },
  {
    "start": 76.56,
    "text": "big deal for me. He was driving to my"
  },
  {
    "start": 79.36,
    "text": "friend's house to drop me off there and"
  },
  {
    "start": 82.24,
    "text": "along the way he threw a plastic pop"
  },
  {
    "start": 85.28,
    "text": "bottle out of his window. I hate"
  },
  {
    "start": 88.159,
    "text": "littering so much. So that was a huge"
  },
  {
    "start": 91.6,
    "text": "turnoff for me. I got so mad I made him"
  },
  {
    "start": 95.68,
    "text": "stop the car and I got out and picked it"
  },
  {
    "start": 98.64,
    "text": "up myself. And the worst part was he"
  },
  {
    "start": 101.759,
    "text": "didn't even apologize or offer to help."
  },
  {
    "start": 105.68,
    "text": "He just sat in his car and watched me"
  },
  {
    "start": 108.88,
    "text": "pick up his trash. That was an immediate"
  },
  {
    "start": 112.64,
    "text": "deal breaker for me. It might have given"
  },
  {
    "start": 115.119,
    "text": "him the ick, too, because I never got"
  },
  {
    "start": 118.0,
    "text": "asked out on a second date, but it's"
  },
  {
    "start": 120.32,
    "text": "probably for the best. My makeup is"
  },
  {
    "start": 123.119,
    "text": "done. I'm on a bit of a time crunch, so"
  },
  {
    "start": 126.799,
    "text": "I'm going to do my hair and get dressed"
  },
  {
    "start": 130.0,
    "text": "very quickly."
  },
  {
    "start": 133.44,
    "text": "This is my final look. My date even came"
  },
  {
    "start": 137.28,
    "text": "to pick me up. Oh my gosh, what a"
  },
  {
    "start": 139.92,
    "text": "gentleman."
  },
  {
    "start": 141.2,
    "text": ">> I leap here."
  },
  {
    "start": 142.319,
    "text": ">> Hey, don't ruin it. [snorts]"
  },
  {
    "start": 144.0,
    "text": "We're wearing matching outfits tonight,"
  },
  {
    "start": 146.879,
    "text": "but obviously I got dressed first and he"
  },
  {
    "start": 150.319,
    "text": "just copied me."
  },
  {
    "start": 151.68,
    "text": ">> Don't lie to people."
  },
  {
    "start": 153.84,
    "text": ">> Time to go. The place we planned on"
  },
  {
    "start": 157.44,
    "text": "going to is closed, of course. So, we're"
  },
  {
    "start": 161.519,
    "text": "heading to Buzzy Navel to try some of"
  },
  {
    "start": 164.72,
    "text": "their winter cocktails."
  },
  {
    "start": 170.16,
    "text": "We got our cocktails [music]"
  },
  {
    "start": 171.68,
    "text": "and these look intense. This one looks"
  },
  {
    "start": 174.64,
    "text": "like a chocolate milkshake. [music]"
  },
  {
    "start": 177.44,
    "text": "Smells strong. [laughter]"
  },
  {
    "start": 179.44,
    "text": "Good luck."
  },
  {
    "start": 180.319,
    "text": ">> Cheers."
  },
  {
    "start": 182.319,
    "text": ">> Ooh."
  },
  {
    "start": 186.0,
    "text": "I prepared a small game for us tonight."
  },
  {
    "start": 188.959,
    "text": "Since we're teaching [music] dating"
  },
  {
    "start": 190.879,
    "text": "English, we can answer some dating"
  },
  {
    "start": 193.28,
    "text": "themed questions. Go ahead and pick one."
  },
  {
    "start": 197.599,
    "text": ">> What celebrity do you think you could"
  },
  {
    "start": 200.959,
    "text": "pull?"
  },
  {
    "start": 202.56,
    "text": ">> Pull."
  },
  {
    "start": 202.959,
    "text": ">> Pull means get as a boyfriend or"
  },
  {
    "start": 205.2,
    "text": "girlfriend or like be able to go on a"
  },
  {
    "start": 206.879,
    "text": "date with. [music]"
  },
  {
    "start": 208.879,
    "text": ">> Let's see your level of confidence."
  },
  {
    "start": 212.239,
    "text": "I mean, I have a my favorite celebrity."
  },
  {
    "start": 215.76,
    "text": ">> Who?"
  },
  {
    "start": 216.799,
    "text": ">> Kelly Sim. [laughter]"
  },
  {
    "start": 219.599,
    "text": ">> Cut."
  },
  {
    "start": 220.56,
    "text": ">> You're full of it. You're full of it."
  },
  {
    "start": 222.879,
    "text": "Come on. Give me something real."
  },
  {
    "start": 224.48,
    "text": ">> I don't want to get any hate comments"
  },
  {
    "start": 226.64,
    "text": "here. Okay."
  },
  {
    "start": 228.08,
    "text": ">> Okay. Okay."
  },
  {
    "start": 229.2,
    "text": ">> Have you ever ghosted someone or been"
  },
  {
    "start": 233.12,
    "text": "ghosted? H"
  },
  {
    "start": 234.879,
    "text": ">> I don't think I have either way."
  },
  {
    "start": 236.56,
    "text": ">> That's good."
  },
  {
    "start": 237.519,
    "text": ">> Me, too. Actually, I hate ghosting."
  },
  {
    "start": 241.28,
    "text": "No, it's never. [laughter]"
  },
  {
    "start": 242.48,
    "text": ">> Okay. Okay."
  },
  {
    "start": 243.68,
    "text": ">> I promise. You know, I'm I would be the"
  },
  {
    "start": 246.72,
    "text": "worst at it. I tell everything. Can't"
  },
  {
    "start": 248.56,
    "text": "help but talk. I'm a talker."
  },
  {
    "start": 251.2,
    "text": ">> What's a major red flag for you?"
  },
  {
    "start": 254.0,
    "text": ">> So, if a girl does this, like, nope,"
  },
  {
    "start": 256.16,
    "text": "can't date her."
  },
  {
    "start": 257.919,
    "text": ">> Someone who never appreciates something"
  },
  {
    "start": 260.959,
    "text": "and then kind of take advantage of like"
  },
  {
    "start": 263.919,
    "text": "my effort or times. And"
  },
  {
    "start": 266.639,
    "text": ">> I'll make sure I say thank you when you"
  },
  {
    "start": 268.16,
    "text": "pay for the bill tonight."
  },
  {
    "start": 270.16,
    "text": "Hint, hint,"
  },
  {
    "start": 271.28,
    "text": ">> hint, hint."
  },
  {
    "start": 272.32,
    "text": ">> Anything for you?"
  },
  {
    "start": 273.28,
    "text": ">> For me, this is very general, but just"
  },
  {
    "start": 276.639,
    "text": "rudeness. Being rude, having no manners,"
  },
  {
    "start": 279.759,
    "text": "especially if we're on a date, the man"
  },
  {
    "start": 282.56,
    "text": "is very rude to the waiter or waitress."
  },
  {
    "start": 286.24,
    "text": ">> I complain a lot. Sometimes"
  },
  {
    "start": 287.919,
    "text": ">> you do, but not in a way where you're"
  },
  {
    "start": 291.12,
    "text": "putting someone down. Like, you're fair."
  },
  {
    "start": 293.759,
    "text": ">> I do [laughter] speak up."
  },
  {
    "start": 295.12,
    "text": ">> That was fun. I want our subscriber to"
  },
  {
    "start": 297.759,
    "text": "write their experience, too."
  },
  {
    "start": 300.72,
    "text": ">> What's a major red flag for you? Let us"
  },
  {
    "start": 304.08,
    "text": "know in the comments."
  },
  {
    "start": 308.88,
    "text": "We finished our drinks and got the bill."
  },
  {
    "start": 312.32,
    "text": "Quick question. In Korea, who usually"
  },
  {
    "start": 315.36,
    "text": "pays on a date?"
  },
  {
    "start": 316.88,
    "text": ">> The girls."
  },
  {
    "start": 318.08,
    "text": ">> You're such a liar. In the US, it really"
  },
  {
    "start": 321.6,
    "text": "depends. Some people are totally fine"
  },
  {
    "start": 325.039,
    "text": "splitting the bill and then some people"
  },
  {
    "start": 327.68,
    "text": "still expect the guy to always pay."
  },
  {
    "start": 330.8,
    "text": "Personally, I think whoever asked for"
  },
  {
    "start": 333.84,
    "text": "the date should be responsible for the"
  },
  {
    "start": 336.08,
    "text": "bill. In [music] that case, it's you"
  },
  {
    "start": 338.32,
    "text": "tonight. [laughter]"
  },
  {
    "start": 340.32,
    "text": "Thank you. I know you said not being"
  },
  {
    "start": 342.639,
    "text": "appreciated is a red flag, so thank you"
  },
  {
    "start": 344.479,
    "text": "so much. Thank you. Thank you. Now,"
  },
  {
    "start": 348.639,
    "text": "we're heading to dinner. We're going to"
  },
  {
    "start": 351.84,
    "text": "a Hong Kong style restaurant since"
  },
  {
    "start": 354.96,
    "text": "that's where we met."
  },
  {
    "start": 357.36,
    "text": ">> Are you kidding me, bro? No. That's all"
  },
  {
    "start": 360.8,
    "text": "right. Let's be spontaneous. This is"
  },
  {
    "start": 363.039,
    "text": "more fun. Our favorite spot in Busousan."
  },
  {
    "start": 366.56,
    "text": "It's called Mikatuka, and it is very"
  },
  {
    "start": 369.039,
    "text": "authentic Mexican food. We come here"
  },
  {
    "start": 371.44,
    "text": "very often, and they're open. Most"
  },
  {
    "start": 374.639,
    "text": "importantly,"
  },
  {
    "start": 377.199,
    "text": "we got our first dish. It's chile."
  },
  {
    "start": 380.16,
    "text": "Chile's"
  },
  {
    "start": 381.039,
    "text": ">> looks spicy."
  },
  {
    "start": 385.68,
    "text": ">> Pretty good. [clears throat]"
  },
  {
    "start": 387.28,
    "text": ">> So, if you remember our first date ever."
  },
  {
    "start": 389.919,
    "text": ">> Wow, that was horrible."
  },
  {
    "start": 392.0,
    "text": ">> I remember very bibli."
  },
  {
    "start": 395.12,
    "text": ">> We were at a party together and we hit"
  },
  {
    "start": 397.68,
    "text": "it off right away. And then you made the"
  },
  {
    "start": 400.319,
    "text": "first move and asked me out on a date."
  },
  {
    "start": 403.44,
    "text": "Well, kind of. I [music] expressed"
  },
  {
    "start": 405.68,
    "text": "interest and told him I wanted to go on"
  },
  {
    "start": 407.919,
    "text": "a date. And then we were supposed to go"
  },
  {
    "start": 410.24,
    "text": "to Victoria speak kind of popular"
  },
  {
    "start": 412.24,
    "text": "tourist attraction in Hong Kong and then"
  },
  {
    "start": 414.319,
    "text": "I was kind of nervous."
  },
  {
    "start": 416.16,
    "text": ">> Why?"
  },
  {
    "start": 416.56,
    "text": ">> I thought you were going to stew me up"
  },
  {
    "start": 418.56,
    "text": "or I don't know."
  },
  {
    "start": 419.52,
    "text": ">> I would never stand you up. Come on. So"
  },
  {
    "start": 421.68,
    "text": "yeah, we went to Victoria's Peak and it"
  },
  {
    "start": 424.96,
    "text": "was an interesting first date."
  },
  {
    "start": 427.719,
    "text": "[laughter]"
  },
  {
    "start": 428.319,
    "text": "It was actually very similar to our date"
  },
  {
    "start": 430.4,
    "text": "tonight. Everything went wrong. It was a"
  },
  {
    "start": 433.039,
    "text": "little bit disastrous."
  },
  {
    "start": 434.479,
    "text": ">> The weather there"
  },
  {
    "start": 435.759,
    "text": ">> was awful. You go there for the view of"
  },
  {
    "start": 439.36,
    "text": "the skyline and there was no view"
  },
  {
    "start": 441.759,
    "text": "because of the fog"
  },
  {
    "start": 443.12,
    "text": ">> and I remember we bought a French fries"
  },
  {
    "start": 446.479,
    "text": "with cheese and it was completely soggy."
  },
  {
    "start": 450.08,
    "text": ">> We didn't get a fork. So we [laughter]"
  },
  {
    "start": 451.44,
    "text": "were like"
  },
  {
    "start": 452.16,
    "text": ">> then I didn't know where to go. So I was"
  },
  {
    "start": 454.319,
    "text": "like oh I thought that you were going to"
  },
  {
    "start": 457.199,
    "text": "Wow. After this we're not going to see"
  },
  {
    "start": 459.919,
    "text": "each other probably."
  },
  {
    "start": 461.12,
    "text": ">> No, I love those kinds of dates to be"
  },
  {
    "start": 463.36,
    "text": "honest. like those are the most"
  },
  {
    "start": 464.72,
    "text": "memorable dates and I thought it was"
  },
  {
    "start": 466.8,
    "text": "hilarious. I could tell that you were"
  },
  {
    "start": 469.12,
    "text": "kind of like bummed out by these things."
  },
  {
    "start": 471.28,
    "text": "So, I thought that was actually really"
  },
  {
    "start": 473.28,
    "text": "cute. [laughter]"
  },
  {
    "start": 477.199,
    "text": ">> I'll say this is the best taco in Busan"
  },
  {
    "start": 480.4,
    "text": "for sure."
  },
  {
    "start": 481.28,
    "text": ">> It's al pastor with cheese."
  },
  {
    "start": 483.919,
    "text": ">> Must try."
  },
  {
    "start": 484.72,
    "text": ">> You won't regret it."
  },
  {
    "start": 487.28,
    "text": ">> Cheers."
  },
  {
    "start": 492.24,
    "text": "I guess our first date was a disaster."
  },
  {
    "start": 494.479,
    "text": "This date was a disaster. But it all"
  },
  {
    "start": 496.72,
    "text": "ended well cuz after Victoria's Peak, we"
  },
  {
    "start": 499.599,
    "text": "kind of started like seeing each other"
  },
  {
    "start": 501.759,
    "text": "casually. It was like a situationship."
  },
  {
    "start": 504.4,
    "text": ">> No, but you totally friends on me"
  },
  {
    "start": 506.24,
    "text": "though."
  },
  {
    "start": 507.199,
    "text": ">> Okay. I did just for a little while"
  },
  {
    "start": 509.199,
    "text": "though."
  },
  {
    "start": 509.68,
    "text": ">> You play hard to get."
  },
  {
    "start": 511.039,
    "text": ">> You have to. You know the chase is part"
  },
  {
    "start": 513.2,
    "text": "of the fun."
  },
  {
    "start": 515.519,
    "text": "We got our last dish. Corn on the cob"
  },
  {
    "start": 518.959,
    "text": "with mayo cheese in Chile. I [laughter]"
  },
  {
    "start": 522.08,
    "text": "feel like this is a bad date food. It's"
  },
  {
    "start": 524.48,
    "text": "so messy."
  },
  {
    "start": 527.279,
    "text": ">> Wow."
  },
  {
    "start": 528.48,
    "text": ">> What's next?"
  },
  {
    "start": 529.44,
    "text": ">> The movies. We got to look for showtimes"
  },
  {
    "start": 532.16,
    "text": "and tickets."
  },
  {
    "start": 533.2,
    "text": ">> You didn't?"
  },
  {
    "start": 533.92,
    "text": ">> I wasn't sure what you'd want to watch,"
  },
  {
    "start": 535.68,
    "text": "so I was being considerate in waiting"
  },
  {
    "start": 538.56,
    "text": "for you. You're welcome. What do you"
  },
  {
    "start": 540.56,
    "text": "want to watch?"
  },
  {
    "start": 540.88,
    "text": ">> Zootopia."
  },
  {
    "start": 541.6,
    "text": ">> Oh, yeah. Zootopia or The Housemaid."
  },
  {
    "start": 544.8,
    "text": "Okay. No Zootopia. No housemade."
  },
  {
    "start": 547.44,
    "text": ">> Is it a revenge from Victoria's Peak?"
  },
  {
    "start": 550.64,
    "text": ">> Junk."
  },
  {
    "start": 552.32,
    "text": "You know what is showing tonight? Solo"
  },
  {
    "start": 554.959,
    "text": "joke season finale. How about it?"
  },
  {
    "start": 558.721,
    "text": "[laughter]"
  },
  {
    "start": 559.279,
    "text": ">> You're in. That means you're in."
  },
  {
    "start": 561.44,
    "text": ">> Popcorn's on you. [laughter]"
  },
  {
    "start": 564.0,
    "text": ">> We're back home in our PJs, snuggled up"
  },
  {
    "start": 567.279,
    "text": "in bed, and ready to watch the season"
  },
  {
    "start": 570.08,
    "text": "finale of Singles Inferno. I think this"
  },
  {
    "start": 573.44,
    "text": "is our dream date these days."
  },
  {
    "start": 575.6,
    "text": ">> Yes. Who are your favorite people on the"
  },
  {
    "start": 578.64,
    "text": "show?"
  },
  {
    "start": 579.04,
    "text": ">> I like Subin."
  },
  {
    "start": 580.24,
    "text": ">> I love watching Mina Su. She's the main"
  },
  {
    "start": 583.839,
    "text": "character here, but I really love Hean."
  },
  {
    "start": 587.36,
    "text": "I think she is so underrated. She just"
  },
  {
    "start": 590.16,
    "text": "has such a quiet confidence and I really"
  },
  {
    "start": 592.8,
    "text": "admire that. And for the guys, I think"
  },
  {
    "start": 597.68,
    "text": ">> Go ahead."
  },
  {
    "start": 598.56,
    "text": ">> My type."
  },
  {
    "start": 599.76,
    "text": ">> Your type [laughter]"
  },
  {
    "start": 601.04,
    "text": ">> would be Egon. He has really good"
  },
  {
    "start": 602.88,
    "text": "banter. Very playful and flirty."
  },
  {
    "start": 605.6,
    "text": ">> He's funny."
  },
  {
    "start": 606.56,
    "text": ">> He is. I like his personality. I think"
  },
  {
    "start": 608.88,
    "text": "that would draw me in. I would fall for"
  },
  {
    "start": 610.88,
    "text": "that. We'll see what happens. I'm"
  },
  {
    "start": 612.56,
    "text": "excited. That's a wrap on date night"
  },
  {
    "start": 615.36,
    "text": "tonight. We're going to watch our show"
  },
  {
    "start": 617.6,
    "text": "and go to bed. It was kind of chaotic"
  },
  {
    "start": 620.32,
    "text": "and nothing went as planned, but I still"
  },
  {
    "start": 622.88,
    "text": "had a lot of fun. See you next time and"
  },
  {
    "start": 625.279,
    "text": "good night."
  },
  {
    "start": 626.399,
    "text": ">> Good night. Who is Mina Sue going to"
  },
  {
    "start": 628.8,
    "text": "choose?"
  }
]