[
  {
    "word": "dehydrated",
    "meaning": "탈수된, 수분이 부족한",
    "examples": [
      "Drink water so you don't get dehydrated.",
      "I felt dehydrated after running in the heat.",
      "The doctor said I was severely dehydrated."
    ],
    "context": [
      "The very first thing I do every single morning is drink some water because I always wake up feeling a little bit dehydrated."
    ]
  },
  {
    "word": "refreshing",
    "meaning": "상쾌한, 기분 좋은",
    "examples": [
      "This iced tea is so refreshing.",
      "It was refreshing to hear a different opinion.",
      "A refreshing breeze came through the window."
    ],
    "context": [
      "Refreshing."
    ]
  }
]